{
  "class": "1bsm",
  "chapter": "Géométrie dans l'espace",
  "sessionDates": [],
  "videos": [],
  "quiz": [
    {
      "id": "q_geo_espace_1",
      "question": "L'équation $x - 2y + 3z - 5 = 0$ est l'équation cartésienne :",
      "type": "mcq",
      "options": [
        {
          "text": "D'une droite",
          "is_correct": false,
          "explanation": null
        },
        {
          "text": "D'un plan",
          "is_correct": false,
          "explanation": null
        },
        {
          "text": "D'une sphère",
          "is_correct": false,
          "explanation": null
        }
      ],
      "steps": []
    }
  ],
  "exercises": [
    {
      "id": "exo_geo_espace_1",
      "title": "Représentation paramétrique",
      "statement": "Donner une représentation paramétrique de la droite (D) passant par le point $A(1,0,2)$ et dirigée par le vecteur $\\vec{u}(2, -1, 1)$.",
      "sub_questions": []
    }
  ],
  "version": "v1.1.0-2c2516"
}