{
  "class": "2bse",
  "chapter": "Dérivation et étude des fonctions",
  "sessionDates": [
    "2025-11-02T01:30:00Z"
  ],
  "quiz": [
  {
    "id": "q_mcq_1",
    "question": "Graphiquement, un 'point anguleux' sur la courbe d'une fonction en $x=a$ signifie que :",
    "options": [
      {
        "text": "La fonction n'est pas continue en $a$.",
        "isCorrect": false
      },
      {
        "text": "La fonction n'est pas dérivable en $a$.",
        "isCorrect": true,
        "explanation": "Un point anguleux indique que la dérivée à gauche et la dérivée à droite en $a$ sont différentes. La fonction n'est donc pas dérivable en ce point."
      },
      {
        "text": "La tangente à la courbe en $a$ est horizontale.",
        "isCorrect": false
      }
    ]
  },
  {
    "id": "q_mcq_2",
    "question": "Quelle est la relation correcte entre la dérivabilité et la continuité d'une fonction en un point ?",
    "options": [
      {
        "text": "Si une fonction est continue en un point, alors elle est dérivable en ce point.",
        "isCorrect": false
      },
      {
        "text": "Si une fonction est dérivable en un point, alors elle est continue en ce point.",
        "isCorrect": true,
        "explanation": "C'est une propriété fondamentale du cours. La dérivabilité est une condition plus forte que la continuité."
      },
      {
        "text": "Une fonction est dérivable si et seulement si elle est continue.",
        "isCorrect": false
      }
    ]
  },
  {
    "id": "q_mcq_3",
    "question": "Une fonction $f$ est dérivable en $a$ si et seulement si :",
    "options": [
      {
        "text": "Elle est continue en $a$.",
        "isCorrect": false
      },
      {
        "text": "Ses dérivées à droite et à gauche en $a$ existent et sont égales.",
        "isCorrect": true,
        "explanation": "C'est la définition même de la dérivabilité en un point : $f'_d(a) = f'_g(a) = l$, où $l$ est un nombre réel fini."
      },
      {
        "text": "Sa courbe admet une tangente au point d'abscisse $a$.",
        "isCorrect": false
      }
    ]
  },
  {
    "id": "q_mcq_4",
    "question": "Si $f'(a) = 0$, que peut-on interpréter géométriquement ?",
    "options": [
      {
        "text": "La courbe de $f$ admet une tangente verticale au point d'abscisse $a$.",
        "isCorrect": false
      },
      {
        "text": "La courbe de $f$ admet une tangente horizontale au point d'abscisse $a$.",
        "isCorrect": true,
        "explanation": "Le nombre dérivé est le coefficient directeur de la tangente. Une pente de 0 signifie que la tangente est horizontale."
      },
      {
        "text": "La fonction $f$ n'est pas définie en $a$.",
        "isCorrect": false
      }
    ]
  },
  {
    "id": "q_mcq_5",
    "question": "L'approximation affine d'une fonction $f$ au voisinage de $a$ est donnée par l'équation de :",
    "options": [
      {
        "text": "La fonction $f$ elle-même.",
        "isCorrect": false
      },
      {
        "text": "La tangente à la courbe de $f$ au point $a$.",
        "isCorrect": true,
        "explanation": "L'équation $y = f'(a)(x-a) + f(a)$ est celle de la tangente, qui constitue la meilleure approximation affine de $f$ localement autour de $a$."
      },
      {
        "text": "Une droite passant par l'origine.",
        "isCorrect": false
      }
    ]
  },
  {
    "id": "q_mcq_6",
    "question": "Si $\\displaystyle \\lim_{x \\to a^+} \\frac{f(x)-f(a)}{x-a} = +\\infty$, alors la courbe de $f$ admet :",
    "options": [
      {
        "text": "Une demi-tangente horizontale à droite en $a$.",
        "isCorrect": false
      },
      {
        "text": "Un point anguleux en $a$.",
        "isCorrect": false
      },
      {
        "text": "Une demi-tangente verticale dirigée vers le haut à droite en $a$.",
        "isCorrect": true,
        "explanation": "Une limite infinie du taux d'accroissement se traduit graphiquement par une tangente verticale."
      }
    ]
  },
  {
    "id": "q_mcq_7",
    "question": "Pour que la fonction réciproque $f^{-1}$ soit dérivable en $f(a)$, une condition essentielle sur $f$ est que :",
    "options": [
      {
        "text": "$f(a)$ doit être non nul.",
        "isCorrect": false
      },
      {
        "text": "$f'(a)$ doit être non nul.",
        "isCorrect": true,
        "explanation": "La formule $(f^{-1})'(f(a)) = 1/f'(a)$ montre que $f'(a)$ ne peut pas être nul, sinon on diviserait par zéro. Géométriquement, cela évite une tangente horizontale sur $f$ qui deviendrait une tangente verticale sur $f^{-1}$."
      },
      {
        "text": "$f$ doit être positive.",
        "isCorrect": false
      }
    ]
  },
  {
    "id": "q_mcq_8",
    "question": "Le signe de la fonction dérivée $f'(x)$ sur un intervalle $I$ nous informe sur :",
    "options": [
      {
        "text": "La position de la courbe de $f$ par rapport à l'axe des abscisses.",
        "isCorrect": false
      },
      {
        "text": "La monotonie (sens de variation) de la fonction $f$.",
        "isCorrect": true,
        "explanation": "Si $f' > 0$, $f$ est croissante. Si $f' < 0$, $f$ est décroissante. C'est l'application principale de la dérivation."
      },
      {
        "text": "La concavité de la courbe de $f$.",
        "isCorrect": false
      }
    ]
  },
  {
    "id": "q_mcq_9",
    "question": "Si $f$ admet un extremum local en $a$ et est dérivable en $a$, alors :",
    "options": [
      {
        "text": "$f'(a)$ doit être positif.",
        "isCorrect": false
      },
      {
        "text": "$f'(a) = 0$.",
        "isCorrect": true,
        "explanation": "C'est une condition nécessaire pour un extremum local dans un intervalle ouvert. La tangente à la courbe y est horizontale."
      },
      {
        "text": "$f'(a)$ n'existe pas.",
        "isCorrect": false
      }
    ]
  },
  {
    "id": "q_mcq_10",
    "question": "Si $f'(c)=0$, peut-on toujours conclure que $f$ admet un extremum local en $c$ ?",
    "options": [
      {
        "text": "Oui, car la tangente est horizontale.",
        "isCorrect": false
      },
      {
        "text": "Non, il faut aussi que la dérivée $f'$ change de signe en $c$.",
        "isCorrect": true,
        "explanation": "C'est la condition suffisante. Si $f'$ s'annule SANS changer de signe, il s'agit d'un point d'inflexion à tangente horizontale."
      },
      {
        "text": "Oui, mais seulement si la fonction est un polynôme.",
        "isCorrect": false
      }
    ]
  },
  {
    "id": "q_mcq_11",
    "question": "Le signe de la dérivée seconde $f''(x)$ sur un intervalle $I$ nous renseigne sur :",
    "options": [
      {
        "text": "Le sens de variation de $f$.",
        "isCorrect": false
      },
      {
        "text": "La concavité de la courbe de $f$.",
        "isCorrect": true,
        "explanation": "Si $f'' > 0$, la fonction est convexe (courbe 'au-dessus' de ses tangentes). Si $f'' < 0$, la fonction est concave (courbe 'en-dessous' de ses tangentes)."
      },
      {
        "text": "L'existence d'asymptotes.",
        "isCorrect": false
      }
    ]
  },
  {
    "id": "q_mcq_12",
    "question": "Un point d'inflexion est un point où :",
    "options": [
      {
        "text": "La fonction dérivée $f'$ s'annule.",
        "isCorrect": false
      },
      {
        "text": "La courbe traverse sa tangente.",
        "isCorrect": true,
        "explanation": "C'est la définition géométrique d'un point d'inflexion. La concavité de la courbe change en ce point."
      },
      {
        "text": "La fonction atteint un maximum ou un minimum.",
        "isCorrect": false
      }
    ]
  },
  {
    "id": "q_mcq_13",
    "question": "Si $\\displaystyle \\lim_{x \\to +\\infty} f(x) = b$ (où $b$ est un réel), que peut-on dire de la courbe de $f$ ?",
    "options": [
      {
        "text": "Elle admet une asymptote verticale d'équation $x=b$.",
        "isCorrect": false
      },
      {
        "text": "Elle admet une asymptote horizontale d'équation $y=b$.",
        "isCorrect": true,
        "explanation": "C'est la définition d'une asymptote horizontale au voisinage de $+\\infty$."
      },
      {
        "text": "Elle admet une asymptote oblique.",
        "isCorrect": false
      }
    ]
  },
  {
    "id": "q_mcq_14",
    "question": "Pour étudier l'existence d'une asymptote oblique, quelle est la première limite à calculer ?",
    "options": [
      {
        "text": "$\\displaystyle \\lim_{x \\to \\infty} (f(x) - x)$",
        "isCorrect": false
      },
      {
        "text": "$\\displaystyle \\lim_{x \\to \\infty} f(x)$",
        "isCorrect": false
      },
      {
        "text": "$\\displaystyle \\lim_{x \\to \\infty} \\frac{f(x)}{x}$",
        "isCorrect": true,
        "explanation": "C'est la première étape cruciale. Si cette limite est un réel fini non nul $a$, on peut alors chercher $b = \\displaystyle \\lim_{x \\to \\infty} (f(x) - ax)$."
      }
    ]
  },
  {
    "id": "q_mcq_15",
    "question": "La dérivée de la fonction composée $(g \\circ f)(x)$ est :",
    "options": [
      {
        "text": "$g'(x) \\times f'(x)$",
        "isCorrect": false
      },
      {
        "text": "$g'(f(x)) \\times f'(x)$",
        "isCorrect": true,
        "explanation": "C'est la formule de la dérivation en chaîne (chain rule). On dérive la fonction 'extérieure' $g$ et on l'évalue en $f(x)$, puis on multiplie par la dérivée de la fonction 'intérieure' $f$."
      },
      {
        "text": "$g'(f'(x))$",
        "isCorrect": false
      }
    ]
  },
  {
    "id": "q_mcq_16",
    "question": "Soit $f$ une fonction dérivable sur $\\mathbb{R}$. Si on sait que $f$ est une fonction paire, que peut-on dire de sa fonction dérivée $f'$ ?",
    "options": [
      {
        "text": "$f'$ est une fonction paire.",
        "isCorrect": false
      },
      {
        "text": "$f'$ est une fonction impaire.",
        "isCorrect": true,
        "explanation": "Si $f(x)=f(-x)$, en dérivant on obtient $f'(x) = -f'(-x)$ en utilisant la dérivation en chaîne, ce qui est la définition d'une fonction impaire."
      },
      {
        "text": "On ne peut rien en déduire.",
        "isCorrect": false
      }
    ]
  },
  {
    "id": "q_mcq_17",
    "question": "La condition $f''(a)=0$ est une condition...",
    "options": [
      {
        "text": "suffisante pour avoir un point d'inflexion en $a$.",
        "isCorrect": false
      },
      {
        "text": "nécessaire pour avoir un point d'inflexion en $a$ (si $f''$ existe).",
        "isCorrect": true,
        "explanation": "Si $f$ est deux fois dérivable et a un point d'inflexion en $a$, alors il est nécessaire que $f''(a)=0$."
      },
      {
        "text": "nécessaire et suffisante pour avoir un point d'inflexion en $a$.",
        "isCorrect": false
      }
    ]
  },
  {
    "id": "q_mcq_18",
    "question": "Quelle information est indispensable pour déterminer l'équation de la tangente à la courbe de $f$ en $a$ ?",
    "options": [
      {
        "text": "Le signe de $f'(a)$ seulement.",
        "isCorrect": false
      },
      {
        "text": "Les valeurs de $f(a)$ et $f'(a)$.",
        "isCorrect": true,
        "explanation": "L'équation est $y=f'(a)(x-a)+f(a)$. Il nous faut le point de passage $(a, f(a))$ et la pente $f'(a)$."
      },
      {
        "text": "La limite de $f$ en $a$.",
        "isCorrect": false
      }
    ]
  },
  {
    "id": "q_mcq_19",
    "question": "Pour la fonction $f(x) = \\sqrt{u(x)}$, sa dérivée existe seulement si :",
    "options": [
      {
        "text": "$u(x)$ est dérivable.",
        "isCorrect": false
      },
      {
        "text": "$u(x)$ est dérivable et $u(x) > 0$.",
        "isCorrect": true,
        "explanation": "Il faut que $u$ soit dérivable et surtout strictement positive pour que la fonction racine carrée soit elle-même dérivable (sa dérivée étant $\\displaystyle \\frac{1}{2\\sqrt{X}})$."
      },
      {
        "text": "$u(x)$ est positive ou nulle.",
        "isCorrect": false
      }
    ]
  },
  {
    "id": "q_mcq_20",
    "question": "La dérivée d'une fonction constante sur un intervalle est :",
    "options": [
      {
        "text": "La fonction nulle.",
        "isCorrect": true,
        "explanation": "Une fonction constante a un taux de variation nul en tout point. Sa pente est toujours 0."
      },
      {
        "text": "La constante elle-même.",
        "isCorrect": false
      },
      {
        "text": "Indéfinie.",
        "isCorrect": false
      }
    ]
  },
  {
    "id": "q_mcq_21",
    "question": "<b>[Type Concours Médecine]</b> Soit $f$ une fonction dérivable telle que $f(2)=3$ et $f'(2)=4$. Soit $f^{-1}$ sa fonction réciproque. Que vaut $(f^{-1})'(3)$ ?",
    "options": [
      {
        "text": "1/4",
        "isCorrect": true,
        "explanation": "On utilise la formule $(f^{-1})'(y_0) = 1/f'(x_0)$ avec $y_0=f(x_0)$. Ici $y_0=3$ et $x_0=2$. Donc, $(f^{-1})'(3) = 1/f'(2) = 1/4$."
      },
      {
        "text": "4",
        "isCorrect": false
      },
      {
        "text": "1/3",
        "isCorrect": false
      }
    ]
  },
  {
    "id": "q_mcq_22",
    "question": "<b>[Type Concours ENSA]</b> Soit $f$ une fonction dérivable sur $\\mathbb{R}$. Laquelle de ces affirmations est TOUJOURS vraie ?",
    "options": [
      {
        "text": "Si $f'(x) \\ge 0$ sur $\\mathbb{R}$, alors $f$ est strictement croissante sur $\\mathbb{R}$.",
        "isCorrect": false
      },
      {
        "text": "Si $f$ est croissante sur $\\mathbb{R}$, alors $f'(x) \\ge 0$ sur $\\mathbb{R}$.",
        "isCorrect": true,
        "explanation": "C'est une propriété directe du cours. La pente d'une fonction croissante est toujours positive ou nulle."
      },
      {
        "text": "Si $f$ admet un maximum global en $a$, alors $f''(a) < 0$.",
        "isCorrect": false
      }
    ]
  },
  {
    "id": "q_mcq_23",
    "question": "<b>[Type Concours ENSAM]</b> On observe la courbe d'une fonction $f$. Elle possède une tangente verticale en $x=-1$ et un point anguleux en $x=2$. Sur quel ensemble la fonction $f'$ est-elle assurément définie ?",
    "options": [
      {
        "text": "$\\mathbb{R}$",
        "isCorrect": false
      },
      {
        "text": "$\\mathbb{R} \\setminus \\{-1, 2\\}$",
        "isCorrect": true,
        "explanation": "Une tangente verticale et un point anguleux sont des points de non-dérivabilité. La fonction dérivée $f'$ existe donc en dehors de ces points (si la fonction est 'lisse' ailleurs)."
      },
      {
        "text": "$\\mathbb{R} \\setminus \\{2\\}$",
        "isCorrect": false
      }
    ]
  }
],
"exercises": [
  {
    "id": "exo_img_3",
    "title": "Étude d'une fonction polynomiale",
    "statement": "Soit la fonction définie sur $\\mathbb{R}$ par : $f(x) = x^3 - 3x + 3$. Et $(\\mathscr{C}_f)$ sa courbe dans un repère orthonormé $(O; \\vec{i}, \\vec{j})$.",
    "sub_questions": [
      { "text": "Calculer les limites de $f(x)$ en $+\\infty$ et en $-\\infty$." },
      { "text": "Étudier les branches infinies de $(\\mathscr{C}_f)$." },
      { "text": "Étudier les variations de $f$ puis dresser le tableau de variations de $f$." },
      { "text": "Étudier la concavité de $(\\mathscr{C}_f)$ en déterminant ses points d'inflexions s'ils existent." },
      { "text": "Montrer que le point $I(0; 3)$ est un centre de symétrie de $(\\mathscr{C}_f)$." },
      { "text": "Construire la courbe $(\\mathscr{C}_f)$." },
      {
        "text": "Soit $g$ la restriction de $f$ sur l'intervalle $I = ]-\\infty; -1]$.",
        "sub_sub_questions": [
          { "text": "Montrer que $g$ admet une fonction réciproque $g^{-1}$ définie sur un intervalle $J$ à déterminer." },
          { "text": "Montrer que l'équation $g(x) = 0$ admet une unique solution $\\alpha$ dans $]-3; -2[$." },
          { "text": "Montrer que $g^{-1}$ est dérivable en 0 puis calculer $(g^{-1})'(0)$." },
          { "text": "Tracer $(\\mathscr{C}_{g^{-1}})$ dans le même repère." }
        ]
      }
    ],
    "hint": [
      {
        "questionNumber": "4",
        "text": "**Points d'inflexion et dérivée seconde** : Un point d'inflexion est un point où la courbe traverse sa tangente, ce qui correspond à un changement de concavité. Calculez $f''(x)$ et étudiez son signe."
      },
      {
        "questionNumber": "5",
        "text": "**Centre de symétrie** : Pour prouver que le point $I(a, b)$ est un centre de symétrie, il faut vérifier la condition $f(a+x) + f(a-x) = 2b$ pour tout $x$ dans le domaine. Ici, $a=0$ et $b=3$."
      },
      {
        "questionNumber": "7b",
        "text": "**Théorème des Valeurs Intermédiaires (TVI)** : Pour prouver l'existence et l'unicité d'une solution, appliquez le corollaire du TVI. Vous devez justifier que la fonction est continue et strictement monotone sur l'intervalle, puis vérifier les valeurs aux bornes."
      }
    ]
  },
  {
    "id": "exo_img_1",
    "title": "Étude d'une fonction rationnelle",
    "statement": "Soit la fonction numérique $f$ définie par : $$f(x) = \\frac{2x}{x^2 + 1}$$ Et $(\\mathscr{C}_f)$ sa courbe dans un repère orthonormé $(O; \\vec{i}, \\vec{j})$.",
    "sub_questions": [
      { "text": "Déterminer $D_f$ puis calculer les limites de $f$ aux bornes de $D_f$." },
      { "text": "Étudier les branches infinies de $(\\mathscr{C}_f)$." },
      { "text": "Montrer que $(\\forall x \\in \\mathbb{R})$, $f'(x) = \\frac{2(1 - x^2)}{(x^2 + 1)^2}$, puis dresser le tableau de variations de $f$." },
      { "text": "Montrer que $(\\forall x \\in \\mathbb{R})$, $f''(x) = \\frac{4x(x^2 - 3)}{(x^2 + 1)^3}$, puis étudier la concavité de $(\\mathscr{C}_f)$." },
      { "text": "Donner une équation de la tangente $(T)$ à $(\\mathscr{C}_f)$ au point O." },
      { "text": "Construire la courbe $(\\mathscr{C}_f)$." },
      {
        "text": "Soit $g$ la restriction de $f$ sur l'intervalle $I = [1; +\\infty[$.",
        "sub_sub_questions": [
          { "text": "Montrer que $g$ admet une fonction réciproque $g^{-1}$ définie sur un intervalle $J$ à déterminer." },
          { "text": "Montrer que $g^{-1}$ est dérivable en $\\frac{4}{5}$ puis calculer $(g^{-1})'(\\frac{4}{5})$." },
          { "text": "Tracer la courbe $(\\mathscr{C}_{g^{-1}})$ dans le même repère." }
        ]
      }
    ],
    "hint": [
      {
        "questionNumber": "1",
        "text": "**Limites d'une fonction rationnelle** : Pour calculer les limites en $+\\infty$ et $-\\infty$, comparez les degrés du numérateur et du dénominateur. La règle des termes de plus haut degré s'applique ici."
      },
      {
        "questionNumber": "3",
        "text": "**Formule de la dérivée d'un quotient** : Pour calculer $f'(x)$, utilisez la formule $\\displaystyle \\left(\\frac{u}{v}\\right)' = \\frac{u'v - uv'}{v^2}$ avec $u(x) = 2x$ et $v(x) = x^2 + 1$."
      },
      {
        "questionNumber": "4",
        "text": "**Dérivée seconde et concavité** : Pour $f''(x)$, il faut dériver $f'(x)$. C'est une nouvelle application de la règle du quotient. Le signe de $f''(x)$ vous donnera la concavité de la courbe."
      },
      {
        "questionNumber": "7b",
        "text": "**Dérivée de la fonction réciproque** : La formule clé est $(g^{-1})'(y_0) = \\frac{1}{g'(x_0)}$. La première étape est de trouver la valeur de $x_0$ telle que $g(x_0) = \\frac{4}{5}$."
      }
    ]
  },
  {
    "id": "exo_img_4",
    "title": "Fonction avec racine carrée",
    "statement": "Soit la fonction numérique définie sur $[0; +\\infty[$ par : $$f(x) = x - 2\\sqrt{x} + 2$$ Et $(\\mathscr{C}_f)$ sa courbe dans un repère orthonormé $(O; \\vec{i}, \\vec{j})$.",
    "sub_questions": [
      {
        "text": "Calculer $\\displaystyle \\lim_{x \\to +\\infty} f(x)$, puis déterminer la branche infinie de $(\\mathscr{C}_f)$."
      },
      {
        "text": "Étudier la dérivabilité de $f$ à droite en 0 puis interpréter géométriquement le résultat obtenu."
      },
      {
        "text": "Étudier la position relative de $(\\mathscr{C}_f)$ par rapport à la droite d'équation $y = x$."
      },
      {
        "text": "Analyse de la dérivée",
        "sub_sub_questions": [
          {
            "text": "Calculer $f'(x)$ pour tout $x \\in ]0; +\\infty[$."
          },
          {
            "text": "Dresser le tableau de variations de $f$."
          }
        ]
      },
      {
        "text": "Tracer $(\\mathscr{C}_f)$ dans le repère $(O; \\vec{i}, \\vec{j})$."
      },
      {
        "text": "Soit $g$ la restriction de $f$ sur l'intervalle $I = [1; +\\infty[$.",
        "sub_sub_questions": [
          {
            "text": "Montrer que $g$ admet une fonction réciproque $g^{-1}$ définie sur un intervalle $J$ à déterminer."
          },
          {
            "text": "Calculer $g(4)$ et montrer que $g^{-1}$ est dérivable en 2 puis calculer $(g^{-1})'(2)$."
          },
          {
            "text": "Montrer que pour tout $x \\in J; g^{-1}(x) = (1 + \\sqrt{x-1})^2$."
          },
          {
            "text": "Tracer $(\\mathscr{C}_{g^{-1}})$ dans le même repère."
          }
        ]
      }
    ],
    "hint": [
      {
        "questionNumber": "2",
        "text": "**Dérivabilité en un point** : Pour étudier la dérivabilité en $0$, vous devez calculer la limite du taux d'accroissement : $\\displaystyle \\lim_{x \\to 0^+} \\frac{f(x) - f(0)}{x - 0}$. Si la limite est infinie, la courbe admet une demi-tangente verticale."
      },
      {
        "questionNumber": "3",
        "text": "**Position relative** : Pour comparer la courbe et la droite, étudiez le signe de la différence $d(x) = f(x) - x$. Si $d(x) > 0$, la courbe est au-dessus de la droite. Si $d(x) < 0$, elle est en dessous."
      },
      {
        "questionNumber": "6c",
        "text": "**Expression de la réciproque** : Posez $y = g(x)$, soit $y = x - 2\\sqrt{x} + 2$. Essayez de reconnaître le début d'une identité remarquable en réarrangeant l'équation sous la forme $(\\sqrt{x} - 1)^2 = y - 1$. Vous pourrez alors isoler $x$."
      }
    ]
  },
  {
    "id": "exo_img_2",
    "title": "Fonction avec racine et asymptote",
    "statement": "Soit $f$ la fonction définie par $f(x) = \\sqrt{x^2 - 1} - x + 1$ et $(\\mathscr{C}_f)$ sa courbe représentative dans un repère orthonormé $(O; \\vec{i}, \\vec{j})$.",
    "sub_questions": [
        {
          "text": "Analyse de la fonction",
          "sub_sub_questions": [
            { "text": "Montrer que $D_f = ]-\\infty; -1] \\cup [1; +\\infty[$." },
            { "text": "Montrer que $\\displaystyle \\lim_{x \\to +\\infty} f(x) = 1$. Interpréter géométriquement le résultat." },
            { "text": "Montrer que la courbe $(\\mathscr{C}_f)$ admet une asymptote oblique en $-\\infty$ d'équation $y = -2x + 1$." }
          ]
        },
        {
          "text": "Exploitation de la dérivée",
          "sub_sub_questions": [
            { "text": "Calculer les deux limites suivantes puis interpréter le résultat géométriquement : $\\displaystyle \\lim_{x \\to -1^+} \\frac{f(x)-f(-1)}{x+1}$ et $\\displaystyle \\lim_{x \\to 1^+} \\frac{f(x)-f(1)}{x-1}$." },
            { "text": "Prouver que $f$ est strictement croissante sur $[1, +\\infty[$ et strictement décroissante sur $]-\\infty, -1]$." },
            { "text": "Donner le tableau de variations de la fonction $f$." },
            { "text": "Tracer $(\\mathscr{C}_f)$ dans le repère $(O; \\vec{i}, \\vec{j})$." }
          ]
        },
        {
          "text": "Étude de la fonction réciproque",
          "sub_sub_questions": [
            { "text": "Montrer que $g$ admet une fonction réciproque $g^{-1}$ définie sur un intervalle $J$ à déterminer, où $g$ est la restriction de $f$ sur $I = [1, +\\infty[$." },
            { "text": "Dresser le tableau de variations de la fonction $g^{-1}$." },
            { "text": "Montrer que pour tout $x \\in J$, on a : $g^{-1}(x) = \\frac{-x^2 + 2x - 2}{2(x-1)}$." }
          ]
        }
    ],
    "hint": [
      {
        "questionNumber": "1a",
        "text": "**Condition d'existence d'une racine carrée** : Le domaine de définition est déterminé par la condition à l'intérieur de la racine. Vous devez résoudre l'inéquation $x^2 - 1 \\ge 0$."
      },
      {
        "questionNumber": "1b",
        "text": "**Forme indéterminée '∞ - ∞'** : Pour lever l'indétermination, la technique classique est de multiplier et diviser par l'expression conjuguée, qui est ici $\\sqrt{x^2 - 1} + x$."
      },
      {
        "questionNumber": "1c",
        "text": "**Recherche d'asymptote oblique** : Pour trouver une asymptote $y=ax+b$, vous devez calculer deux limites : d'abord $a = \\displaystyle \\lim_{x \\to -\\infty} \\frac{f(x)}{x}$, puis $b = \\displaystyle \\lim_{x \\to -\\infty} (f(x) - ax)$."
      },
      {
        "questionNumber": "3c",
        "text": "**Trouver l'expression de la réciproque** : Pour trouver $g^{-1}(x)$, posez $y = g(x)$ et isolez $x$ en fonction de $y$. L'étape clé est d'isoler le terme avec la racine carrée avant d'élever les deux côtés de l'équation au carré."
      }
    ]
  },
  {
    "id": "exo_img_5",
    "title": "Étude avec fonction auxiliaire",
    "statement": "",
    "sub_questions": [
      {
        "text": "Soit $g$ la fonction définie sur $\\mathbb{R}$ par $$g(x) = 1 + \\frac{x}{\\sqrt{x^2+1}}$$",
        "sub_sub_questions": [
          {
            "text": "Vérifier que pour tout réel $x$ on a : $g'(x) = \\displaystyle \\frac{1}{(x^2+1)\\sqrt{x^2+1}}$."
          },
          {
            "text": "Étudier les variations de $g$ et en déduire que pour tout réel $x : g(x) > 0$."
          }
        ]
      },
      {
        "text": "Soit $f$ la fonction définie sur $\\mathbb{R}$ par $f(x) = x - 1 + \\sqrt{x^2+1}$ et $(\\mathscr{C}_f)$ sa courbe représentative dans un repère orthonormé $(O, \\vec{i}, \\vec{j})$.",
        "sub_sub_questions": [
          {
            "text": "Calculer $\\displaystyle \\lim_{x \\to +\\infty} f(x)$."
          },
          {
            "text": "Montrer que $\\displaystyle \\lim_{x \\to -\\infty} f(x) = -1$. Interpréter graphiquement le résultat obtenu."
          },
          {
            "text": "Montrer que la droite $(\\Delta)$ d'équation $y = 2x - 1$ est une asymptote à $(\\mathscr{C}_f)$ au voisinage de $+\\infty$."
          }
        ]
      },
      {
        "text": "Lien entre $f$ et $g$",
        "sub_sub_questions": [
          {
            "text": "Vérifier que pour tout réel $x$ on a : $f'(x) = g(x)$."
          },
          {
            "text": "Dresser le tableau de variation de $f$."
          }
        ]
      },
      {
        "text": "Tracer $(\\Delta)$ et $(\\mathscr{C}_f)$ dans le repère $(O, \\vec{i}, \\vec{j})$."
      },
      {
        "text": "Étude de la fonction réciproque",
        "sub_sub_questions": [
          {
            "text": "Montrer que $f$ admet une fonction réciproque $f^{-1}$ définie sur un intervalle $J$ que l'on déterminera."
          },
          {
            "text": "Calculer $(f^{-1})'(\\sqrt{2})$."
          },
          {
            "text": "Tracer $(\\mathscr{C}_{f^{-1}})$ la courbe représentative de $f^{-1}$ dans le même repère."
          }
        ]
      }
    ],
    "hint": [
      {
        "questionNumber": "1a",
        "text": "**Dérivation d'un quotient et d'une racine** : Pour dériver $\\frac{x}{\\sqrt{x^2+1}}$, utilisez la formule $\\left(\\frac{u}{v}\\right)'$. N'oubliez pas que la dérivée de $\\sqrt{v}$ est $\\frac{v'}{2\\sqrt{v}}$."
      },
      {
        "questionNumber": "2b",
        "text": "**Lever une indétermination '∞ - ∞'** : Il s'agit d'une forme indéterminée. Pensez à multiplier et diviser par l'expression conjuguée de $x + \\sqrt{x^2+1}$ pour lever l'indétermination."
      },
      {
        "questionNumber": "2c",
        "text": "**Vérification de l'asymptote oblique** : L'énoncé vous donne la droite. Il suffit donc de montrer que la limite de la différence, $\\displaystyle \\lim_{x \\to +\\infty} [f(x) - (2x-1)]$, est égale à 0."
      },
      {
        "questionNumber": "5b",
        "text": "**Théorème de la dérivée de la réciproque** : Appliquez la formule $(f^{-1})'(y_0) = \\frac{1}{f'(x_0)}$. Votre première tâche est de trouver $x_0$ tel que $f(x_0) = \\sqrt{2}$. Ensuite, calculez $f'(x_0)$."
      }
    ]
  },
  {
    "id": "exo_img_6",
    "title": "Étude avancée d'une fonction rationnelle",
    "statement": "Considérons la fonction $f$ définie par : $$f(x) = \\frac{2x^3 + 4x^2 + x}{(x+1)^2}$$ Et $(\\mathscr{C}_f)$ sa courbe représentative dans le plan rapporté à un repère orthogonal.",
    "sub_questions": [
      { "text": "Déterminer $D_f$." },
      { "text": "Calculer $\\displaystyle \\lim_{x \\to -\\infty} f(x)$ et $\\displaystyle \\lim_{x \\to +\\infty} f(x)$." },
      { "text": "Calculer $\\displaystyle \\lim_{x \\to -1} f(x)$ et interpréter géométriquement le résultat." },
      { "text": "Vérifier que pour tout $x \\in D_f : f(x) = 2x - \\frac{x}{(x+1)^2}$." },
      { "text": "Montrer que la droite $(D)$ d'équation $y = 2x$ est asymptote oblique à $(\\mathscr{C}_f)$ en $-\\infty$ et $+\\infty$." },
      { "text": "Calculer $f(x) - 2x$ et étudier la position relative de $(\\mathscr{C}_f)$ par rapport à $(D)$." },
      { "text": "Vérifier que pour tout $x \\in D_f : f'(x) = \\frac{2x^3 + 6x^2 + 7x + 1}{(x+1)^3}$." },
      {
        "text": "En utilisant les informations sur la dérivée $f'$:",
        "sub_sub_questions": [
          { "text": "Montrer que l'équation $f'(x) = 0$ admet une unique solution $\\alpha$ sur $D_f$." },
          { "text": "Dresser le tableau de variations de $f$ sur $D_f$." }
        ]
      },
      { "text": "Déterminer l'équation de la tangente $(T)$ au graphe de $f$ au point d'abscisse $-2$." },
      { "text": "Déterminer l'intersection de $(\\mathscr{C}_f)$ avec l'axe des abscisses." },
      {
        "text": "Soit $h$ la restriction de $f$ sur $I = [0, +\\infty[$.",
        "sub_sub_questions": [
          { "text": "Montrer que $h$ admet une fonction réciproque $h^{-1}$ définie sur un domaine $J$ à déterminer." },
          { "text": "Dresser le tableau de variations de $h^{-1}$." },
          { "text": "Montrer que la droite $(D')$ d'équation $y = \\frac{1}{2}x$ est asymptote oblique à $(\\mathscr{C}_{h^{-1}})$ en $+\\infty$." }
        ]
      },
      { "text": "Tracer $(T)$, $(D)$, $(\\mathscr{C}_f)$ et $(\\mathscr{C}_{h^{-1}})$ dans le même repère. (On donne $f(\\alpha) \\approx -0,1$ et $\\alpha \\approx -0,2$)." }
    ],
    "hint": [
      {
        "questionNumber": "4",
        "text": "**Vérification par mise au même dénominateur** : Pour vérifier l'égalité, partez de l'expression $2x - \\frac{x}{(x+1)^2}$ et mettez tout au même dénominateur. Vous devriez retomber sur l'expression initiale de $f(x)$."
      },
      {
        "questionNumber": "5",
        "text": "**Asymptote oblique** : Pour montrer que $y=2x$ est une asymptote oblique, il suffit de prouver que $\\displaystyle \\lim_{x \\to \\pm\\infty} [f(x) - 2x] = 0$. La question 4 vous donne directement cette différence !"
      },
      {
        "questionNumber": "6",
        "text": "**Position relative** : La position de la courbe par rapport à son asymptote dépend du signe de la différence $f(x) - 2x$. Utilisez l'expression de la question 4 pour étudier ce signe facilement."
      },
      {
        "questionNumber": "11c",
        "text": "**Symétrie des asymptotes** : Si $y=ax+b$ est une asymptote à $(\\mathscr{C}_h)$, alors la droite symétrique par rapport à $y=x$, qui est $x=ay+b$, est une asymptote à $(\\mathscr{C}_{h^{-1}})$. Isolez $y$ dans cette équation pour trouver l'asymptote de la réciproque."
      }
    ]
  }
],
  "version": "7a26b0364a64e783c608e5514326d8a3_updated_v2_all_images"
}